argcomplete/__init__.py
argcomplete/_check_console_script.py
argcomplete/_check_module.py
argcomplete/completers.py
argcomplete/exceptions.py
argcomplete/finders.py
argcomplete/io.py
argcomplete/lexers.py
argcomplete/py.typed
argcomplete/shell_integration.py
argcomplete/bash_completion.d/_python-argcomplete
argcomplete/packages/__init__.py
argcomplete/packages/_argparse.py
argcomplete/packages/_shlex.py
argcomplete/scripts/__init__.py
argcomplete/scripts/activate_global_python_argcomplete.py
argcomplete/scripts/python_argcomplete_check_easy_install_script.py
argcomplete/scripts/register_python_argcomplete.py
argcomplete-3.5.0.dist-info/LICENSE.rst
argcomplete-3.5.0.dist-info/METADATA
argcomplete-3.5.0.dist-info/NOTICE
argcomplete-3.5.0.dist-info/WHEEL
argcomplete-3.5.0.dist-info/entry_points.txt
argcomplete-3.5.0.dist-info/top_level.txt
argcomplete-3.5.0.dist-info/RECORD
