Metadata-Version: 2.1
Name: argcomplete
Version: 3.5.0
Summary: Bash tab completion for argparse
Home-page: https://github.com/kislyuk/argcomplete
Author: Andrey Kislyuk
Author-email: kislyuk@gmail.com
License: Apache Software License
Project-URL: Documentation, https://kislyuk.github.io/argcomplete
Project-URL: Source Code, https://github.com/kislyuk/argcomplete
Project-URL: Issue Tracker, https://github.com/kislyuk/argcomplete/issues
Project-URL: Change Log, https://github.com/kislyuk/argcomplete/blob/master/Changes.rst
Platform: MacOS X
Platform: Posix
Classifier: Environment :: Console
Classifier: Intended Audience :: Developers
Classifier: License :: OSI Approved :: Apache Software License
Classifier: Operating System :: MacOS :: MacOS X
Classifier: Operating System :: POSIX
Classifier: Programming Language :: Python
Classifier: Programming Language :: Python :: 3
Classifier: Programming Language :: Python :: 3.7
Classifier: Programming Language :: Python :: 3.8
Classifier: Programming Language :: Python :: 3.9
Classifier: Programming Language :: Python :: 3.10
Classifier: Programming Language :: Python :: 3.11
Classifier: Programming Language :: Python :: 3.12
Classifier: Programming Language :: Python :: Implementation :: CPython
Classifier: Programming Language :: Python :: Implementation :: PyPy
Classifier: Development Status :: 5 - Production/Stable
Classifier: Topic :: Software Development
Classifier: Topic :: Software Development :: Libraries :: Python Modules
Classifier: Topic :: System :: Shells
Classifier: Topic :: Terminals
Requires-Python: >=3.8
License-File: LICENSE.rst
License-File: NOTICE
Provides-Extra: test
Requires-Dist: coverage; extra == "test"
Requires-Dist: pexpect; extra == "test"
Requires-Dist: wheel; extra == "test"
Requires-Dist: ruff; extra == "test"
Requires-Dist: mypy; extra == "test"
